odoo10_addon_mrp_bom_location-10.0.1.0.0.99.dev4-py2.7-nspkg.pth
odoo/addons/mrp_bom_location/README.rst
odoo/addons/mrp_bom_location/__init__.py
odoo/addons/mrp_bom_location/__manifest__.py
odoo/addons/mrp_bom_location/i18n/de.po
odoo/addons/mrp_bom_location/i18n/mrp_bom_location.pot
odoo/addons/mrp_bom_location/models/__init__.py
odoo/addons/mrp_bom_location/models/mrp_bom.py
odoo/addons/mrp_bom_location/report/__init__.py
odoo/addons/mrp_bom_location/report/bom_structure.py
odoo/addons/mrp_bom_location/static/description/icon.png
odoo/addons/mrp_bom_location/views/mrp_view.xml
odoo/addons/mrp_bom_location/views/report_mrpbomstructure.xml
odoo10_addon_mrp_bom_location-10.0.1.0.0.99.dev4.dist-info/METADATA
odoo10_addon_mrp_bom_location-10.0.1.0.0.99.dev4.dist-info/RECORD
odoo10_addon_mrp_bom_location-10.0.1.0.0.99.dev4.dist-info/WHEEL
odoo10_addon_mrp_bom_location-10.0.1.0.0.99.dev4.dist-info/namespace_packages.txt
odoo10_addon_mrp_bom_location-10.0.1.0.0.99.dev4.dist-info/top_level.txt
